.gitmodules
CMakeLists.txt
LICENSE
Makefile
README.md
setup.py
Fred/__init__.py
Fred/hd_fs.py
Fred/median.py
Fred/stabbing.py
Fred_Frechet.egg-info/PKG-INFO
Fred_Frechet.egg-info/SOURCES.txt
Fred_Frechet.egg-info/dependency_links.txt
Fred_Frechet.egg-info/not-zip-safe
Fred_Frechet.egg-info/requires.txt
Fred_Frechet.egg-info/top_level.txt
include/.gitignore
include/bounding.hpp
include/clustering.hpp
include/config.hpp
include/coreset.hpp
include/curve.hpp
include/dynamic_time_warping.hpp
include/frechet.hpp
include/grid.hpp
include/interval.hpp
include/jl_transform.hpp
include/point.hpp
include/random.hpp
include/simplification.hpp
include/types.hpp
logo/logo.png
logo/logo.svg
src/.gitignore
src/bounding.cpp
src/clustering.cpp
src/config.cpp
src/curve.cpp
src/dynamic_time_warping.cpp
src/frechet.cpp
src/fred_python_wrapper.cpp
src/interval.cpp
src/jl_transform.cpp
src/point.cpp
src/simplification.cpp
test/test.py