Metadata-Version: 2.1
Name: Fred-Frechet
Version: 1.12.4
Summary: A fast, scalable and light-weight C++ Fréchet distance library, exposed to python and focused on (k,l)-clustering of polygonal curves.
Home-page: http://fred.dennisrohde.work
Author: Dennis Rohde
Author-email: dennis.rohde@tu-dortmund.de
License-File: LICENSE
